{
  "_class": "symbolMaster",
  "allowsOverrides": true,
  "backgroundColor": {
    "_class": "color",
    "alpha": 1,
    "blue": 0.2588235294117647,
    "green": 0.1803921568627452,
    "red": 0.1411764705882353
  },
  "booleanOperation": 0,
  "changeIdentifier": 8534,
  "clippingMaskMode": 0,
  "do_objectID": "403BAF38-AA80-4A6A-8BEF-7C09D70C29B8",
  "exportOptions": {
    "_class": "exportOptions",
    "exportFormats": [
    ],
    "includedLayerIds": [
    ],
    "layerOptions": 0,
    "shouldTrim": false
  },
  "frame": {
    "_class": "rect",
    "constrainProportions": false,
    "height": 24,
    "width": 24,
    "x": 7458,
    "y": 1430
  },
  "groupLayout": {
    "_class": "MSImmutableFreeformGroupLayout"
  },
  "hasBackgroundColor": true,
  "hasClickThrough": true,
  "hasClippingMask": false,
  "horizontalRulerData": {
    "_class": "rulerData",
    "base": 0,
    "guides": [
    ]
  },
  "includeBackgroundColorInExport": false,
  "includeBackgroundColorInInstance": false,
  "includeInCloudUpload": true,
  "isFixedToViewport": false,
  "isFlippedHorizontal": false,
  "isFlippedVertical": false,
  "isFlowHome": false,
  "isLocked": false,
  "isVisible": true,
  "layerListExpandedType": 1,
  "layers": [
    {
      "class": "rectangle",
      "id": "F1317959-BE8F-4EA6-AC0E-B134AC8633E5"
    },
    {
      "class": "rectangle",
      "id": "642A9521-553F-41D7-AE39-E3480953DFA2"
    },
    {
      "class": "shapePath",
      "id": "19D48BED-62DC-49F0-BCB0-02F67CE1297B"
    },
    {
      "class": "oval",
      "id": "34033522-BD65-4CB3-B25C-E6D16E2F7E49"
    },
    {
      "class": "shapePath",
      "id": "94BE72F1-F464-40CC-963F-00C8BF07B97A"
    },
    {
      "class": "shapePath",
      "id": "9C5A5D11-C598-460F-8D9C-F87C5CF2E751"
    }
  ],
  "maintainScrollPosition": false,
  "name": "Organisms / Left Hand Nav / icons /Gallery",
  "nameIsFixed": true,
  "overrideProperties": [
    {
      "_class": "MSImmutableOverrideProperty",
      "canOverride": true,
      "overrideName": "642A9521-553F-41D7-AE39-E3480953DFA2_image"
    },
    {
      "_class": "MSImmutableOverrideProperty",
      "canOverride": true,
      "overrideName": "94BE72F1-F464-40CC-963F-00C8BF07B97A_layerStyle"
    },
    {
      "_class": "MSImmutableOverrideProperty",
      "canOverride": true,
      "overrideName": "94BE72F1-F464-40CC-963F-00C8BF07B97A_image"
    },
    {
      "_class": "MSImmutableOverrideProperty",
      "canOverride": true,
      "overrideName": "19D48BED-62DC-49F0-BCB0-02F67CE1297B_image"
    },
    {
      "_class": "MSImmutableOverrideProperty",
      "canOverride": true,
      "overrideName": "19D48BED-62DC-49F0-BCB0-02F67CE1297B_layerStyle"
    },
    {
      "_class": "MSImmutableOverrideProperty",
      "canOverride": true,
      "overrideName": "9C5A5D11-C598-460F-8D9C-F87C5CF2E751_image"
    },
    {
      "_class": "MSImmutableOverrideProperty",
      "canOverride": true,
      "overrideName": "642A9521-553F-41D7-AE39-E3480953DFA2_layerStyle"
    },
    {
      "_class": "MSImmutableOverrideProperty",
      "canOverride": true,
      "overrideName": "9C5A5D11-C598-460F-8D9C-F87C5CF2E751_layerStyle"
    }
  ],
  "presetDictionary": {
  },
  "resizesContent": false,
  "resizingConstraint": 63,
  "resizingType": 0,
  "rotation": 0,
  "shouldBreakMaskChain": true,
  "style": {
    "_class": "style",
    "blur": {
      "_class": "blur",
      "center": "{0.5, 0.5}",
      "isEnabled": false,
      "motionAngle": 0,
      "radius": 10,
      "saturation": 1,
      "type": 0
    },
    "borderOptions": {
      "_class": "borderOptions",
      "dashPattern": [
      ],
      "isEnabled": true,
      "lineCapStyle": 0,
      "lineJoinStyle": 0
    },
    "borders": [
    ],
    "colorControls": {
      "_class": "colorControls",
      "brightness": 0,
      "contrast": 1,
      "hue": 0,
      "isEnabled": true,
      "saturation": 1
    },
    "contextSettings": {
      "_class": "graphicsContextSettings",
      "blendMode": 0,
      "opacity": 1
    },
    "do_objectID": "5FD17EDA-D462-437B-8AC0-F77BF2BA44D6",
    "endMarkerType": 0,
    "fills": [
    ],
    "innerShadows": [
    ],
    "miterLimit": 10,
    "shadows": [
    ],
    "startMarkerType": 0,
    "windingRule": 1
  },
  "symbolID": "4E1C8E10-8AC1-421E-927E-0BCD9704DCDF",
  "userInfo": {
    "com.animaapp.stc-sketch-plugin": {
      "kModelPropertiesKey": {
      }
    }
  },
  "verticalRulerData": {
    "_class": "rulerData",
    "base": 0,
    "guides": [
    ]
  }
}